sphinx_celery/__init__.py
sphinx_celery/apicheck.py
sphinx_celery/autodocargspec.py
sphinx_celery/builders.py
sphinx_celery/conf.py
sphinx_celery/configcheck.py
sphinx_celery/github_issues.py
sphinx_celery/setting_crossref.py
sphinx_celery/signal_crossref.py
sphinx_celery/theme.conf
sphinx_celery/utils.py
sphinx_celery/static/celery.css_t
sphinx_celery/templates/page.html
sphinx_celery/tests/__init__.py
sphinx_celery-2.1.3.dist-info/AUTHORS
sphinx_celery-2.1.3.dist-info/LICENSE
sphinx_celery-2.1.3.dist-info/METADATA
sphinx_celery-2.1.3.dist-info/WHEEL
sphinx_celery-2.1.3.dist-info/entry_points.txt
sphinx_celery-2.1.3.dist-info/top_level.txt
sphinx_celery-2.1.3.dist-info/RECORD
