Metadata-Version: 2.1
Name: sphinx-celery
Version: 2.1.3
Summary: Sphinx Celery Theme.
Home-page: http://github.com/celery/sphinx_celery
Author: Ask Solem
Author-email: ask@celeryproject.org
License: BSD
Keywords: sphinx docs
Platform: any
Classifier: Development Status :: 5 - Production/Stable
Classifier: Programming Language :: Python
Classifier: Programming Language :: Python :: 3
Classifier: Programming Language :: Python :: 3.7
Classifier: Programming Language :: Python :: 3.8
Classifier: Programming Language :: Python :: 3.9
Classifier: License :: OSI Approved :: BSD License
Classifier: Intended Audience :: Developers
Classifier: Operating System :: OS Independent
License-File: LICENSE
License-File: AUTHORS
Requires-Dist: Sphinx >=2.0.0
